gimageckr/__init__.py
gimageckr/crawler.py
gimageckr-0.0.5.dist-info/LICENSE
gimageckr-0.0.5.dist-info/METADATA
gimageckr-0.0.5.dist-info/WHEEL
gimageckr-0.0.5.dist-info/top_level.txt
gimageckr-0.0.5.dist-info/RECORD
